{
	"name": "WOODLANDS CLINIC",
	"tel": "62696681",
	"fax": "62691502",
	"licensee": "WOODLANDS CLINIC PTE. LTD.",
	"licensePeriod": "01/01/2014 to 31/12/2018",
	"licenseClass": "[ 5 Years ]",
	"address": "BLK 131 MARSILING RISE, #01-204 Singapore 730131",
	"detailedServices": {
		"General Medical": true
	},
	"programmes": [
		"Chronic Disease Management Programme (CDMP)",
		"Community Health Assistance Scheme (CHAS)"
	],
	"id": "9401898",
	"coordinates": [
		103.778613439344,
		1.43847983955612
	],
	"svy21": [
		21912.1571563855,
		46685.3823676091
	],
	"planningArea": "WD",
	"neighbours": [
		"MD",
		"SB",
		"SK"
	]
}