{
	"name": "DENTAL CLINIC",
	"tel": "65555177",
	"fax": "65555177",
	"licensee": "Health Promotion Board",
	"licensePeriod": "01/04/2015 to 31/03/2020",
	"licenseClass": "[ 5 Years ]",
	"address": "21 ADMIRALTY DR,, CANBERRA PRIMARY SCHOOL, Singapore 757714",
	"doctorInCharge": [
		{
			"name": "Chee Ching Teng",
			"qualifications": [
				"BDS (University of Singapore, Singapore) 1974"
			],
			"specialties": []
		}
	],
	"detailedServices": {
		"General Dental": true
	},
	"operatingHours": {
		"Monday to Thursday": "08:00 am to 05:30 pm",
		"Friday and Friday": "08:00 am to 05:00 pm"
	},
	"id": "9402850",
	"coordinates": [
		103.815839476605,
		1.45130467584564
	],
	"svy21": [
		26054.8552722549,
		48103.4229366668
	],
	"planningArea": "SB",
	"neighbours": [
		"MD",
		"WD",
		"SM",
		"YS"
	]
}