{
	"name": "ALVIN HONG NEUROSURGERY",
	"tel": "67338803",
	"fax": "68360949",
	"licensee": "Hong Neurosurgery Pte. Ltd.",
	"licensePeriod": "18/08/2015 to 17/08/2020",
	"licenseClass": "[ 5 Years ]",
	"address": "3 Mount Elizabeth, Mount Elizabeth Medical Centre, #14-14 Singapore 228510",
	"doctorInCharge": [
		{
			"name": "Alvin Hong",
			"qualifications": [
				"MB Bchir (University of Cambridge, United Kingdom) 1986",
				"FRCSEd (Gen Surg) (Royal College of Surgeons of Edinburgh, United Kingdom) 1989",
				"FRCS (Neurosurgery) (Royal College of Surgeons of Edinburgh, United Kingdom) 1994"
			],
			"specialties": [
				"Neurosurgery"
			]
		}
	],
	"detailedServices": {
		"Specialist Medical": [
			"Neurosurgery"
		]
	},
	"operatingHours": {
		"Monday to Friday": "09:00 am to 05:00 pm",
		"Saturday": "09:00 am to 12:00 pm"
	},
	"id": "9405276",
	"coordinates": [
		103.835439337571,
		1.30516521383703
	],
	"svy21": [
		28236.0209034365,
		31944.0563655663
	],
	"planningArea": "CA",
	"neighbours": [
		"BM",
		"KL",
		"MP",
		"NV",
		"TN"
	]
}