{
	"name": "DR CINDY'S MEDICAL AESTHETICS",
	"tel": "67864433",
	"fax": "67868878",
	"licensee": "ART OF CINDY PTE. LTD.",
	"licensePeriod": "14/05/2016 to 13/05/2018",
	"licenseClass": "[ 2 Years ( 2B ) ]",
	"hciCode": "12C0066",
	"address": "10 TAMPINES CENTRAL 1, TAMPINES ONE, #05-12 Singapore 529536",
	"doctorInCharge": [
		{
			"name": "Yang Cindy",
			"qualifications": [
				"MBBS (National University of Singapore, Singapore) 1993"
			],
			"specialties": []
		}
	],
	"detailedServices": {
		"General Medical": true
	},
	"operatingHours": {
		"Public Holiday": [
			[
				"00:00",
				"18:00"
			]
		],
		"Monday": [
			[
				"01:00",
				"21:00"
			]
		],
		"Tuesday": [
			[
				"01:00",
				"21:00"
			]
		],
		"Wednesday": [
			[
				"01:00",
				"21:00"
			]
		],
		"Thursday": [
			[
				"01:00",
				"21:00"
			]
		],
		"Friday": [
			[
				"01:00",
				"21:00"
			]
		],
		"Saturday": [
			[
				"00:00",
				"20:00"
			]
		],
		"Sunday": [
			[
				"00:00",
				"19:00"
			]
		]
	},
	"id": "12C0066",
	"coordinates": [
		103.9450718,
		1.3542564
	],
	"svy21": [
		40436.86,
		37372.59
	],
	"planningArea": "TM",
	"neighbours": [
		"BD",
		"PR",
		"PL",
		"CH"
	]
}