{
	"name": "REFRESH LASER CLINIC",
	"tel": "68449768",
	"fax": "66341598",
	"licensee": "Refresh Laser Clinic Bedok Pte. Ltd.",
	"licensePeriod": "05/12/2015 to 04/12/2017",
	"licenseClass": "[ 5 Years ]",
	"hciCode": "13M0344",
	"address": "311 NEW UPPER CHANGI ROAD, BEDOK MALL, #B1-18 Singapore 467360",
	"doctorInCharge": [
		{
			"name": "Char Li Shing",
			"qualifications": [
				"MBBS (National University of Singapore, Singapore) 1992"
			],
			"specialties": [
				"Family Physician"
			]
		}
	],
	"detailedServices": {
		"General Medical": true
	},
	"operatingHours": {
		"Monday": [
			[
				"01:30",
				"16:30"
			],
			[
				"17:30",
				"21:00"
			]
		],
		"Tuesday": [
			[
				"01:30",
				"16:30"
			],
			[
				"17:30",
				"21:00"
			]
		],
		"Wednesday": [
			[
				"01:30",
				"16:30"
			],
			[
				"17:30",
				"21:00"
			]
		],
		"Thursday": [
			[
				"01:30",
				"16:30"
			],
			[
				"17:30",
				"21:00"
			]
		],
		"Friday": [
			[
				"01:30",
				"16:30"
			],
			[
				"17:30",
				"21:00"
			]
		],
		"Saturday": [
			[
				"01:30",
				"16:30"
			],
			[
				"17:30",
				"21:00"
			]
		],
		"Sunday": [
			[
				"01:30",
				"16:30"
			],
			[
				"17:30",
				"21:00"
			]
		]
	},
	"id": "13M0344",
	"combinedSpecialties": [
		"Family Physician",
		"General Medical"
	],
	"coordinates": [
		103.9292677,
		1.3247721
	],
	"svy21": [
		38678.17,
		34112.29
	],
	"planningArea": "BD",
	"neighbours": [
		"GL",
		"HG",
		"MP",
		"PL",
		"TM"
	],
	"insurance": []
}