{
	"name": "DENTAL CLINIC",
	"tel": "65640866",
	"fax": "65640866",
	"licensee": "Health Promotion Board",
	"licensePeriod": "06/03/2017 to 05/03/2019",
	"licenseClass": "[ 2 Years ( 2A ) ]",
	"hciCode": "15D0066",
	"address": "30 BUKIT BATOK STREET 32, ST. ANTHONY'S PRIMARY SCHOOL, Singapore 659401",
	"doctorInCharge": [
		{
			"name": "THAM SAI SOO",
			"qualifications": [
				"BDS (University of Singapore, Singapore) 1976"
			],
			"specialties": []
		}
	],
	"detailedServices": {
		"General Dental": true
	},
	"operatingHours": {
		"Monday": [
			[
				"08:00",
				"17:30"
			]
		],
		"Tuesday": [
			[
				"08:00",
				"17:30"
			]
		],
		"Wednesday": [
			[
				"08:00",
				"17:30"
			]
		],
		"Thursday": [
			[
				"08:00",
				"17:30"
			]
		],
		"Friday": [
			[
				"08:00",
				"17:00"
			]
		]
	},
	"id": "15D0066",
	"combinedSpecialities": [
		"General Dental"
	],
	"coordinates": [
		103.7492519,
		1.3641168
	],
	"svy21": [
		18644.37,
		38462.78
	],
	"planningArea": "BK",
	"neighbours": [
		"BP",
		"BT",
		"JE",
		"TH",
		"CK",
		"CL"
	],
	"insurance": []
}