{
	"name": "ADAM ROAD MEDICAL CENTRE PSYCHIATRIC & PSYCHOLOGICAL SERVICES",
	"tel": "64667777",
	"fax": "64670254",
	"licensee": "MD SPECIALIST HEALTHCARE PTE LTD",
	"licensePeriod": "24/02/2017 to 23/02/2019",
	"licenseClass": "[ 2 Years ( 2A ) ]",
	"hciCode": "17C0046",
	"address": "559 Bukit Timah Road, King's Arcade, #01-02 Singapore 269695",
	"doctorInCharge": [
		{
			"name": "Ung Eng Khean, Kenneth",
			"qualifications": [
				"MBBS (University of Newcastle Upon Tyne, United Kingdom) 1987",
				"MRC Psych (Royal College of Psychiatrists, United Kingdom) 1992"
			],
			"specialties": [
				"Psychiatry"
			]
		}
	],
	"detailedServices": {
		"Specialist Medical": [
			"Psychiatry"
		]
	},
	"id": "17C0046",
	"combinedSpecialities": [
		"Psychiatry",
		"Specialist Medical"
	],
	"coordinates": [
		103.8107213,
		1.3232103
	],
	"svy21": [
		25485.14,
		33939.4
	],
	"planningArea": "BT",
	"neighbours": [
		"BK",
		"BP",
		"NV",
		"QT",
		"CC",
		"TN",
		"CL"
	]
}