{
	"name": "HUI CLINIC + SURGERY",
	"tel": "64588596",
	"fax": "64588596",
	"licensee": "HUMANAE VITAE PTE LTD",
	"licensePeriod": "01/01/2014 to 31/12/2018",
	"licenseClass": "[ 5 Years ]",
	"hciCode": "9400714",
	"address": "BLK 157 ANG MO KIO AVE 4, #01-566 Singapore 560157",
	"doctorInCharge": [
		{
			"name": "HUI KEEM PENG JOHN",
			"qualifications": [
				"MBBS (National University of Singapore, Singapore) 1989"
			],
			"specialties": [
				"Family Physician"
			]
		}
	],
	"detailedServices": {
		"General Medical": true
	},
	"programmes": [
		"Chronic Disease Management Programme (CDMP)",
		"Community Health Assistance Scheme (CHAS)",
		"Integrated Screening Programme (ISP) "
	],
	"operatingHrs": {
		"Monday": [
			[
				"08:30",
				"14:30"
			],
			[
				"14:00",
				"16:30"
			],
			[
				"17:30",
				"20:30"
			]
		],
		"Tuesday": [
			[
				"08:30",
				"14:30"
			],
			[
				"14:00",
				"16:30"
			],
			[
				"17:30",
				"20:30"
			]
		],
		"Wednesday": [
			[
				"08:30",
				"14:30"
			],
			[
				"14:00",
				"16:30"
			]
		],
		"Thursday": [
			[
				"08:30",
				"14:30"
			],
			[
				"14:00",
				"16:30"
			]
		],
		"Friday": [
			[
				"08:30",
				"14:30"
			],
			[
				"14:00",
				"16:30"
			]
		],
		"Saturday": [
			[
				"08:30",
				"14:30"
			]
		],
		"Sunday": [
			[
				"08:30",
				"01:00"
			]
		]
	},
	"id": "9400714",
	"insurance": [
		"CHAS"
	],
	"rawOperatingHours": {
		"Monday to Tuesday": "08:30 am to 12:30 pm, 02:00 pm to 04:30 pm, 05:30 pm to 08:30 pm",
		"Wednesday to Friday": "08:30 am to 12:30 pm, 02:00 pm to 04:30 pm",
		"Saturday": "08:30 am to 12:30 pm",
		"Sunday": "08:30 am to 11:00 am"
	},
	"combinedSpecialties": [
		"Family Physician",
		"General Medical"
	],
	"coordinates": [
		103.8393951,
		1.3753056
	],
	"svy21": [
		28676.24,
		39699.82
	],
	"planningArea": "AM",
	"neighbours": [
		"BS",
		"SE",
		"SG",
		"CC",
		"YS"
	]
}